lemippy-0.1.dev5.dist-info/RECORD
lemippy-0.1.dev5.dist-info/top_level.txt
lemippy-0.1.dev5.dist-info/METADATA
lemippy-0.1.dev5.dist-info/WHEEL
lib/__init__.py
lemippy/highs_bindings.cpython-37m-x86_64-linux-gnu.so
lemippy/__init__.py
lemippy/highs_bindings.cpp
lemippy/lemip.py
lemippy/tests/__init__.py
lemippy/tests/test_highspy.py
lemippy.libs/libhighs-2b9e77ab.so.1.5.0
