Metadata-Version: 2.1
Name: lemippy
Version: 0.1.dev5
Summary: Python interface to lemip
Maintainer-email: sunyong4@lenovo.com
License: MIT
Classifier: Programming Language :: Python :: 3
Classifier: Programming Language :: Python :: 3.6
Classifier: Programming Language :: Python :: 3.7
Classifier: Programming Language :: Python :: 3.8
Classifier: Programming Language :: Python :: 3.9
Classifier: Programming Language :: Python :: 3.10
Classifier: Programming Language :: Python :: 3.11
Classifier: License :: OSI Approved :: MIT License
Requires-Python: >=3.6
Requires-Dist: pybind11
Requires-Dist: numpy
Requires-Dist: pyomo
